molino/__init__.py
molino/forge.py
molino/manager.py
molino/scope.py
molino/transformer_abstract.py
molino/resources/__init__.py
molino/resources/collection.py
molino/resources/item.py
molino/resources/null.py
molino/resources/resource_abstract.py
molino/serializers/__init__.py
molino/serializers/data_serializer.py
molino/serializers/json_api_serializer.py
molino/serializers/plain_serializer.py
molino/serializers/serializer_abstract.py
molino/serializers/sld_data_serializer.py
molino/support/__init__.py
molino/support/snake_case.py
molino-0.2.3.dist-info/LICENSE
molino-0.2.3.dist-info/METADATA
molino-0.2.3.dist-info/WHEEL
molino-0.2.3.dist-info/top_level.txt
molino-0.2.3.dist-info/RECORD
