Metadata-Version: 2.1
Name: molino
Version: 0.2.3
Summary: Presentation and transformation layer for complex data output
Home-page: https://github.com/xaamin/data-forge
Author: Benjamín Martínez Mateos
Author-email: xaamin@outlook.com
Classifier: Programming Language :: Python :: 3
Classifier: License :: OSI Approved :: MIT License
Classifier: Operating System :: OS Independent
Requires-Python: >=3.0
License-File: LICENSE
